[
  {
    "creator_id": null,
    "platform": "youtube",
    "content_id": "_HU5DI3CGZc",
    "content_type": "video",
    "title": "LG LED Lightfair - 3",
    "description": "LG's Lighting innovation technology is designed to drive a better payback.",
    "url": "https://youtube.com/watch?v=_HU5DI3CGZc",
    "view_count": 378,
    "like_count": 3,
    "comment_count": 0,
    "published_at": "2017-11-30T19:27:13Z",
    "metadata": {
      "duration": "PT44S",
      "thumbnail_url": "https://i.ytimg.com/vi/_HU5DI3CGZc/hqdefault.jpg",
      "tags": [
        "LG",
        "LG Electronics",
        "LED",
        "Lighting",
        "LED Lighting",
        "Lightfair"
      ],
      "category_id": "22",
      "default_language": "en",
      "favorite_count": 0
    }
  },
  {
    "creator_id": null,
    "platform": "youtube",
    "content_id": "RvPZ-WbdL_Y",
    "content_type": "video",
    "title": "LG LED Lightfair - 2",
    "description": "LG's Lighting capabilities combined with Autani's EnergyCenter\u2122 software platform take system integration through ZigBee wireless to the next level.",
    "url": "https://youtube.com/watch?v=RvPZ-WbdL_Y",
    "view_count": 169,
    "like_count": 2,
    "comment_count": 0,
    "published_at": "2017-11-30T19:24:56Z",
    "metadata": {
      "duration": "PT44S",
      "thumbnail_url": "https://i.ytimg.com/vi/RvPZ-WbdL_Y/hqdefault.jpg",
      "tags": [
        "LG",
        "LG Electronics",
        "LED",
        "Lighting",
        "LED Lighting"
      ],
      "category_id": "22",
      "default_language": "en",
      "favorite_count": 0
    }
  },
  {
    "creator_id": null,
    "platform": "youtube",
    "content_id": "6lnWkzzS5JE",
    "content_type": "video",
    "title": "LG LED Lightfair - 1",
    "description": "LG's LED Lighting provides a simpler way to create a complex control system.",
    "url": "https://youtube.com/watch?v=6lnWkzzS5JE",
    "view_count": 150,
    "like_count": 3,
    "comment_count": 0,
    "published_at": "2017-11-30T18:59:51Z",
    "metadata": {
      "duration": "PT42S",
      "thumbnail_url": "https://i.ytimg.com/vi/6lnWkzzS5JE/hqdefault.jpg",
      "tags": [
        "LG",
        "LG Electronics",
        "LED",
        "LED Lighting",
        "Lighting",
        "Lightfair",
        "Energy Efficiency"
      ],
      "category_id": "22",
      "default_language": "en",
      "favorite_count": 0
    }
  },
  {
    "creator_id": null,
    "platform": "youtube",
    "content_id": "_zQrEiZDrEk",
    "content_type": "video",
    "title": "LG LED Lightfair 2017",
    "description": "Watch to learn what differentiates LG's LED Lighting fixtures from other lighting technologies, as seen at Lightfair 2017.",
    "url": "https://youtube.com/watch?v=_zQrEiZDrEk",
    "view_count": 81,
    "like_count": 1,
    "comment_count": 0,
    "published_at": "2017-11-09T19:27:20Z",
    "metadata": {
      "duration": "PT3M58S",
      "thumbnail_url": "https://i.ytimg.com/vi/_zQrEiZDrEk/hqdefault.jpg",
      "tags": [
        "LED Lighting",
        "Energy Savings",
        "Energy Efficient",
        "Lighting Technology",
        "Troffers",
        "Retrofits",
        "Autoni",
        "ZigBee"
      ],
      "category_id": "22",
      "default_language": "en",
      "favorite_count": 0
    }
  },
  {
    "creator_id": null,
    "platform": "youtube",
    "content_id": "lFQiPKlJl2Y",
    "content_type": "video",
    "title": "LG LED Lighting",
    "description": "Watch to learn how LG's LED future proof solutions for retail, office, industrial or school environments offer rapid payback of your investments and insure supply chain reliability.",
    "url": "https://youtube.com/watch?v=lFQiPKlJl2Y",
    "view_count": 1729,
    "like_count": 4,
    "comment_count": 0,
    "published_at": "2016-05-11T21:13:53Z",
    "metadata": {
      "duration": "PT2M58S",
      "thumbnail_url": "https://i.ytimg.com/vi/lFQiPKlJl2Y/hqdefault.jpg",
      "tags": [
        "LED",
        "lighting",
        "LG LED",
        "LG",
        "integrated supply chain",
        "supply chain",
        "LED lighting",
        "save money",
        "save energy",
        "energy efficient",
        "energy efficient lighting"
      ],
      "category_id": "22",
      "default_language": "en",
      "favorite_count": 0
    }
  },
  {
    "creator_id": null,
    "platform": "youtube",
    "content_id": "aRlJy7f_G8I",
    "content_type": "video",
    "title": "LG Sensor Connect",
    "description": "",
    "url": "https://youtube.com/watch?v=aRlJy7f_G8I",
    "view_count": 2657,
    "like_count": 3,
    "comment_count": 2,
    "published_at": "2016-04-15T15:29:29Z",
    "metadata": {
      "duration": "PT4M32S",
      "thumbnail_url": "https://i.ytimg.com/vi/aRlJy7f_G8I/hqdefault.jpg",
      "tags": [],
      "category_id": "22",
      "default_language": "en",
      "favorite_count": 0
    }
  }
]